{
	"@context": "https://hubmapconsortium.github.io/ccf-ontology/ccf-context.jsonld",
	"@id": "9a4354a8-ad67-4b91-bca6-8af78395dcf8",
	"@type": "SpatialEntity",
	"creator": "Bhargav Desai",
	"label": "f_g_pancreas_bb_A-13-II",
	"creation_date": "2023-07-22",
	"dimension_units": "millimeter",
	"placement": {
		"@context": "https://hubmapconsortium.github.io/ccf-ontology/ccf-context.jsonld",
		"@id": "9a4354a8-ad67-4b91-bca6-8af78395dcf8_placement",
		"@type": "SpatialPlacement",
		"target": "http://purl.org/ccf/latest/ccf.owl#VHFPancreas",
		"placement_date": "2023-07-22",
		"scaling_units": "ratio",
		"rotation_order": "XYZ",
		"rotation_units": "degree",
		"translation_units": "millimeter",
		"x_scaling": 1.0,
		"y_scaling": 1.0,
		"z_scaling": 1.0,
		"x_rotation": 0.0,
		"y_rotation": 0.0,
		"z_rotation": 0.0,
		"x_translation": 58.745711986200234,
		"y_translation": 52.81944312326575,
		"z_translation": 55.35164693504159
	},
	"x_dimension": 19.074449497596664,
	"y_dimension": 17.117470184659865,
	"z_dimension": 19.369436603972417
}