{
	"@context": "https://hubmapconsortium.github.io/ccf-ontology/ccf-context.jsonld",
	"@id": "c091673b-cf77-4878-accd-ddf5845e5776",
	"@type": "SpatialEntity",
	"creator": "Bhargav Desai",
	"label": "f_g_pancreas_bb_A-16-II",
	"creation_date": "2023-07-22",
	"dimension_units": "millimeter",
	"placement": {
		"@context": "https://hubmapconsortium.github.io/ccf-ontology/ccf-context.jsonld",
		"@id": "c091673b-cf77-4878-accd-ddf5845e5776_placement",
		"@type": "SpatialPlacement",
		"target": "http://purl.org/ccf/latest/ccf.owl#VHMPancreas",
		"placement_date": "2023-07-22",
		"scaling_units": "ratio",
		"rotation_order": "XYZ",
		"rotation_units": "degree",
		"translation_units": "millimeter",
		"x_scaling": 1.0,
		"y_scaling": 1.0,
		"z_scaling": 1.0,
		"x_rotation": 0.0,
		"y_rotation": 0.0,
		"z_rotation": 0.0,
		"x_translation": 33.12908617162403,
		"y_translation": 33.975999566886905,
		"z_translation": 58.213271696924984
	},
	"x_dimension": 15.85579957732071,
	"y_dimension": 6.896207351368866,
	"z_dimension": 21.21835035255662
}